diff_cov_lint/__init__.py
diff_cov_lint/coverage.py
diff_cov_lint/diff.py
diff_cov_lint/lint.py
diff_cov_lint/main.py
diff_cov_lint-0.1.4.dist-info/LICENSE
diff_cov_lint-0.1.4.dist-info/METADATA
diff_cov_lint-0.1.4.dist-info/WHEEL
diff_cov_lint-0.1.4.dist-info/entry_points.txt
diff_cov_lint-0.1.4.dist-info/top_level.txt
diff_cov_lint-0.1.4.dist-info/RECORD
