Metadata-Version: 2.1
Name: diff-cov-lint
Version: 0.1.4
Summary: Linting and coverage reports for diff only
Home-page: https://gitlab.com/sVerentsov/diff-cov-lint
Author: Sergey Verentsov
Author-email: verentsov@eora.ru
License: UNKNOWN
Platform: UNKNOWN
Classifier: Programming Language :: Python :: 3
Classifier: License :: OSI Approved :: MIT License
Classifier: Operating System :: OS Independent
Requires-Python: >=3.6
Requires-Dist: fire (==0.2.1)
Requires-Dist: gitpython (==3.0.8)
Requires-Dist: unidiff (==0.5.5)
